mail_builder/__init__.py
mail_builder/builder.py
mail_builder/views.py
mail_builder/templatetags/__init__.py
mail_builder/templatetags/mailbuilder.py
django_mail_builder-0.5.1.dist-info/LICENSE
django_mail_builder-0.5.1.dist-info/METADATA
django_mail_builder-0.5.1.dist-info/WHEEL
django_mail_builder-0.5.1.dist-info/top_level.txt
django_mail_builder-0.5.1.dist-info/RECORD
