Metadata-Version: 2.1
Name: django-mail-builder
Version: 0.5.1
Summary: Simple template-based EmailMessage builder for Django
Author-email: Curtis Maloney <curtis@tinbrain.net>
License: BSD
Project-URL: Source Code, https://github.com/funkybob/django-mail-builder
Project-URL: Documentation, https://django-mail-builder.readthedocs.io/en/
Classifier: Environment :: Web Environment
Classifier: Framework :: Django
Classifier: License :: OSI Approved :: BSD License
Classifier: Operating System :: OS Independent
Classifier: Programming Language :: Python
Classifier: Programming Language :: Python :: 3.10
Classifier: Programming Language :: Python :: 3.11
Classifier: Programming Language :: Python :: 3.12
Classifier: Programming Language :: Python :: Implementation :: PyPy
Requires-Python: >=3.10
License-File: LICENSE
Requires-Dist: django
